{"metadata":{"rubocop_version":"0.39.0","ruby_engine":"ruby","ruby_version":"2.2.4","ruby_patchlevel":"230","ruby_platform":"x86_64-linux-gnu"},"files":[{"path":"app/models/nomination.rb","offenses":[
{"severity":"convention","message":"Missing top-level module documentation comment.","cop_name":"Style/Documentation","corrected":null,"location":{"line":13,"column":1,"length":6}},
{"severity":"convention","message":"Missing top-level class documentation comment.","cop_name":"Style/Documentation","corrected":null,"location":{"line":34,"column":1,"length":5}},
{"severity":"convention","message":"Missing top-level module documentation comment.","cop_name":"Style/Documentation","corrected":null,"location":{"line":35,"column":3,"length":6}},
{"severity":"convention","message":"Line is too long. [91/80] (https://github.com/bbatsov/ruby-style-guide#80-character-limits)","cop_name":"Metrics/LineLength","corrected":null,"location":{"line":35,"column":81,"length":11}},
{"severity":"convention","message":"Missing top-level module documentation comment.","cop_name":"Style/Documentation","corrected":null,"location":{"line":39,"column":3,"length":6}},
{"severity":"convention","message":"Line is too long. [97/80] (https://github.com/bbatsov/ruby-style-guide#80-character-limits)","cop_name":"Metrics/LineLength","corrected":null,"location":{"line":39,"column":81,"length":17}},
{"severity":"convention","message":"Missing top-level module documentation comment.","cop_name":"Style/Documentation","corrected":null,"location":{"line":43,"column":3,"length":6}},
{"severity":"convention","message":"Line is too long. [110/80] (https://github.com/bbatsov/ruby-style-guide#80-character-limits)","cop_name":"Metrics/LineLength","corrected":null,"location":{"line":49,"column":81,"length":30}},
{"severity":"convention","message":"Missing top-level module documentation comment.","cop_name":"Style/Documentation","corrected":null,"location":{"line":53,"column":3,"length":6}},
{"severity":"convention","message":"Line is too long. [160/80] (https://github.com/bbatsov/ruby-style-guide#80-character-limits)","cop_name":"Metrics/LineLength","corrected":null,"location":{"line":56,"column":81,"length":80}},
{"severity":"convention","message":"Method has too many lines. [15/10] (https://github.com/bbatsov/ruby-style-guide#short-methods)","cop_name":"Metrics/MethodLength","corrected":null,"location":{"line":63,"column":5,"length":629}},
{"severity":"convention","message":"Tab detected. (https://github.com/bbatsov/ruby-style-guide#spaces-indentation)","cop_name":"Style/Tab","corrected":true,"location":{"line":64,"column":1,"length":3}},
{"severity":"convention","message":"Use 2 (not -1) spaces for indentation. (https://github.com/bbatsov/ruby-style-guide#spaces-indentation)","cop_name":"Style/IndentationWidth","corrected":true,"location":{"line":64,"column":4,"length":1}},
{"severity":"warning","message":"Useless assignment to variable - `units`. (https://github.com/bbatsov/ruby-style-guide#underscore-unused-vars)","cop_name":"Lint/UselessAssignment","corrected":null,"location":{"line":64,"column":7,"length":5}},
{"severity":"convention","message":"Tab detected. (https://github.com/bbatsov/ruby-style-guide#spaces-indentation)","cop_name":"Style/Tab","corrected":true,"location":{"line":65,"column":1,"length":3}},
{"severity":"convention","message":"Use 2 (not 0) spaces for indentation. (https://github.com/bbatsov/ruby-style-guide#spaces-indentation)","cop_name":"Style/IndentationWidth","corrected":true,"location":{"line":65,"column":7,"length":0}},
{"severity":"convention","message":"Incorrect indentation detected (column 0 instead of 3).","cop_name":"Style/CommentIndentation","corrected":true,"location":{"line":66,"column":1,"length":37}},
{"severity":"convention","message":"Incorrect indentation detected (column 3 instead of 6).","cop_name":"Style/CommentIndentation","corrected":true,"location":{"line":66,"column":4,"length":37}},
{"severity":"convention","message":"Incorrect indentation detected (column 6 instead of 8).","cop_name":"Style/CommentIndentation","corrected":true,"location":{"line":66,"column":7,"length":37}},
{"severity":"convention","message":"Tab detected. (https://github.com/bbatsov/ruby-style-guide#spaces-indentation)","cop_name":"Style/Tab","corrected":true,"location":{"line":67,"column":1,"length":3}},
{"severity":"convention","message":"Inconsistent indentation detected.","cop_name":"Style/IndentationConsistency","corrected":true,"location":{"line":67,"column":7,"length":364}},
{"severity":"convention","message":"Tab detected. (https://github.com/bbatsov/ruby-style-guide#spaces-indentation)","cop_name":"Style/Tab","corrected":true,"location":{"line":68,"column":1,"length":4}},
{"severity":"convention","message":"Tab detected. (https://github.com/bbatsov/ruby-style-guide#spaces-indentation)","cop_name":"Style/Tab","corrected":true,"location":{"line":69,"column":1,"length":3}},
{"severity":"convention","message":"Tab detected. (https://github.com/bbatsov/ruby-style-guide#spaces-indentation)","cop_name":"Style/Tab","corrected":true,"location":{"line":70,"column":1,"length":4}},
{"severity":"convention","message":"Tab detected. (https://github.com/bbatsov/ruby-style-guide#spaces-indentation)","cop_name":"Style/Tab","corrected":true,"location":{"line":71,"column":1,"length":4}},
{"severity":"convention","message":"Tab detected. (https://github.com/bbatsov/ruby-style-guide#spaces-indentation)","cop_name":"Style/Tab","corrected":true,"location":{"line":72,"column":1,"length":4}},
{"severity":"convention","message":"Tab detected. (https://github.com/bbatsov/ruby-style-guide#spaces-indentation)","cop_name":"Style/Tab","corrected":true,"location":{"line":73,"column":1,"length":4}},
{"severity":"convention","message":"Tab detected. (https://github.com/bbatsov/ruby-style-guide#spaces-indentation)","cop_name":"Style/Tab","corrected":true,"location":{"line":74,"column":1,"length":5}},
{"severity":"convention","message":"Tab detected. (https://github.com/bbatsov/ruby-style-guide#spaces-indentation)","cop_name":"Style/Tab","corrected":true,"location":{"line":75,"column":1,"length":4}},
{"severity":"convention","message":"Tab detected. (https://github.com/bbatsov/ruby-style-guide#spaces-indentation)","cop_name":"Style/Tab","corrected":true,"location":{"line":76,"column":1,"length":5}},
{"severity":"convention","message":"Tab detected. (https://github.com/bbatsov/ruby-style-guide#spaces-indentation)","cop_name":"Style/Tab","corrected":true,"location":{"line":77,"column":1,"length":4}},
{"severity":"convention","message":"Tab detected. (https://github.com/bbatsov/ruby-style-guide#spaces-indentation)","cop_name":"Style/Tab","corrected":true,"location":{"line":78,"column":1,"length":3}},
{"severity":"convention","message":"Tab detected. (https://github.com/bbatsov/ruby-style-guide#spaces-indentation)","cop_name":"Style/Tab","corrected":true,"location":{"line":79,"column":1,"length":3}},
{"severity":"convention","message":"Extra blank line detected.","cop_name":"Style/EmptyLines","corrected":true,"location":{"line":82,"column":1,"length":1}},
{"severity":"convention","message":"Use 2 (not 6) spaces for indentation. (https://github.com/bbatsov/ruby-style-guide#spaces-indentation)","cop_name":"Style/IndentationWidth","corrected":true,"location":{"line":84,"column":7,"length":6}},
{"severity":"convention","message":"Use `next` to skip iteration. (https://github.com/bbatsov/ruby-style-guide#no-nested-conditionals)","cop_name":"Style/Next","corrected":true,"location":{"line":84,"column":13,"length":18}},
{"severity":"convention","message":"Tab detected. (https://github.com/bbatsov/ruby-style-guide#spaces-indentation)","cop_name":"Style/Tab","corrected":true,"location":{"line":85,"column":1,"length":4}},
{"severity":"convention","message":"Use 2 (not -2) spaces for indentation. (https://github.com/bbatsov/ruby-style-guide#spaces-indentation)","cop_name":"Style/IndentationWidth","corrected":true,"location":{"line":85,"column":5,"length":2}},
{"severity":"convention","message":"Use `next` to skip iteration. (https://github.com/bbatsov/ruby-style-guide#no-nested-conditionals)","cop_name":"Style/Next","corrected":true,"location":{"line":85,"column":5,"length":18}},
{"severity":"convention","message":"Inconsistent indentation detected.","cop_name":"Style/IndentationConsistency","corrected":true,"location":{"line":85,"column":11,"length":64}},
{"severity":"convention","message":"Tab detected. (https://github.com/bbatsov/ruby-style-guide#spaces-indentation)","cop_name":"Style/Tab","corrected":true,"location":{"line":86,"column":1,"length":5}},
{"severity":"convention","message":"Inconsistent indentation detected.","cop_name":"Style/IndentationConsistency","corrected":true,"location":{"line":86,"column":11,"length":49}},
{"severity":"convention","message":"Tab detected. (https://github.com/bbatsov/ruby-style-guide#spaces-indentation)","cop_name":"Style/Tab","corrected":true,"location":{"line":87,"column":1,"length":5}},
{"severity":"convention","message":"Inconsistent indentation detected.","cop_name":"Style/IndentationConsistency","corrected":true,"location":{"line":87,"column":11,"length":67}},
{"severity":"convention","message":"Tab detected. (https://github.com/bbatsov/ruby-style-guide#spaces-indentation)","cop_name":"Style/Tab","corrected":true,"location":{"line":88,"column":1,"length":5}},
{"severity":"convention","message":"Tab detected. (https://github.com/bbatsov/ruby-style-guide#spaces-indentation)","cop_name":"Style/Tab","corrected":true,"location":{"line":89,"column":1,"length":6}},
{"severity":"convention","message":"Tab detected. (https://github.com/bbatsov/ruby-style-guide#spaces-indentation)","cop_name":"Style/Tab","corrected":true,"location":{"line":90,"column":1,"length":5}},
{"severity":"convention","message":"Incorrect indentation detected (column 1 instead of 8).","cop_name":"Style/CommentIndentation","corrected":true,"location":{"line":90,"column":2,"length":8}},
{"severity":"convention","message":"Missing top-level module documentation comment.","cop_name":"Style/Documentation","corrected":null,"location":{"line":111,"column":3,"length":6}},
{"severity":"convention","message":"Line is too long. [87/80] (https://github.com/bbatsov/ruby-style-guide#80-character-limits)","cop_name":"Metrics/LineLength","corrected":null,"location":{"line":111,"column":81,"length":7}},
{"severity":"convention","message":"Line is too long. [237/80] (https://github.com/bbatsov/ruby-style-guide#80-character-limits)","cop_name":"Metrics/LineLength","corrected":null,"location":{"line":113,"column":81,"length":157}},
{"severity":"convention","message":"Line is too long. [153/80] (https://github.com/bbatsov/ruby-style-guide#80-character-limits)","cop_name":"Metrics/LineLength","corrected":null,"location":{"line":114,"column":81,"length":73}},
{"severity":"convention","message":"Missing top-level module documentation comment.","cop_name":"Style/Documentation","corrected":null,"location":{"line":123,"column":3,"length":6}},
{"severity":"convention","message":"Missing top-level module documentation comment.","cop_name":"Style/Documentation","corrected":null,"location":{"line":124,"column":5,"length":6}},
{"severity":"warning","message":"Useless assignment to variable - `nested_constants`. (https://github.com/bbatsov/ruby-style-guide#underscore-unused-vars)","cop_name":"Lint/UselessAssignment","corrected":null,"location":{"line":126,"column":9,"length":16}},
{"severity":"convention","message":"Line is too long. [93/80] (https://github.com/bbatsov/ruby-style-guide#80-character-limits)","cop_name":"Metrics/LineLength","corrected":null,"location":{"line":129,"column":81,"length":13}},
{"severity":"convention","message":"Line is too long. [85/80] (https://github.com/bbatsov/ruby-style-guide#80-character-limits)","cop_name":"Metrics/LineLength","corrected":null,"location":{"line":132,"column":81,"length":5}},
{"severity":"convention","message":"Line is too long. [83/80] (https://github.com/bbatsov/ruby-style-guide#80-character-limits)","cop_name":"Metrics/LineLength","corrected":null,"location":{"line":133,"column":81,"length":3}},
{"severity":"convention","message":"Line is too long. [107/80] (https://github.com/bbatsov/ruby-style-guide#80-character-limits)","cop_name":"Metrics/LineLength","corrected":null,"location":{"line":134,"column":81,"length":27}},
{"severity":"convention","message":"Line is too long. [82/80] (https://github.com/bbatsov/ruby-style-guide#80-character-limits)","cop_name":"Metrics/LineLength","corrected":null,"location":{"line":139,"column":81,"length":2}},
{"severity":"convention","message":"Line is too long. [96/80] (https://github.com/bbatsov/ruby-style-guide#80-character-limits)","cop_name":"Metrics/LineLength","corrected":null,"location":{"line":141,"column":81,"length":16}},
{"severity":"convention","message":"Line is too long. [83/80] (https://github.com/bbatsov/ruby-style-guide#80-character-limits)","cop_name":"Metrics/LineLength","corrected":null,"location":{"line":146,"column":81,"length":3}},
{"severity":"warning","message":"Useless assignment to variable - `message`. (https://github.com/bbatsov/ruby-style-guide#underscore-unused-vars)","cop_name":"Lint/UselessAssignment","corrected":null,"location":{"line":152,"column":9,"length":7}},
{"severity":"warning","message":"Useless assignment to variable - `message`. (https://github.com/bbatsov/ruby-style-guide#underscore-unused-vars)","cop_name":"Lint/UselessAssignment","corrected":null,"location":{"line":160,"column":9,"length":7}},
{"severity":"warning","message":"`end` at 163, 5 is not aligned with `module` at 124, 4.","cop_name":"Lint/EndAlignment","corrected":false,"location":{"line":163,"column":6,"length":3}},
{"severity":"warning","message":"Useless assignment to variable - `message`. (https://github.com/bbatsov/ruby-style-guide#underscore-unused-vars)","cop_name":"Lint/UselessAssignment","corrected":null,"location":{"line":166,"column":7,"length":7}},
{"severity":"warning","message":"Useless assignment to variable - `message`. (https://github.com/bbatsov/ruby-style-guide#underscore-unused-vars)","cop_name":"Lint/UselessAssignment","corrected":null,"location":{"line":174,"column":7,"length":7}}]}],"summary":{"offense_count":67,"target_file_count":1,"inspected_file_count":1}}